komodo_dkarv/__init__.py
komodo_dkarv/lib.py
komodo_dkarv-0.0.1.dist-info/METADATA
komodo_dkarv-0.0.1.dist-info/WHEEL
komodo_dkarv-0.0.1.dist-info/RECORD
