Metadata-Version: 2.4
Name: komodo_dkarv
Version: 0.0.1
Summary: Komodo client API
Project-URL: Homepage, https://github.com/dkarv/komodo-src
Project-URL: Issues, https://github.com/dkarv/komodo-src/issues
Author-email: David Punzet <punzet.david@gmail.com>
License-Expression: MIT
Classifier: Operating System :: OS Independent
Classifier: Programming Language :: Python :: 3
Requires-Python: >=3.9
